{
    "info": {
		"_postman_id"   : "d9bc3afc-fd40-5505-b57f-8f5d5118e01b",
		"name"          : "@app - iam/permission",
		"schema"        : "https://schema.getpostman.com/json/collection/v2.1.0/collection.json"
    },
    "item": [
        {
			"name": "GraphQL - iamCreatePermission",
			"request": {
				"method": "POST",
				"header": [
                ],
				"body": {
					"mode": "graphql",
					"graphql": {
						"query": "mutation ($payload:IamCreatePermissionInput!)\n{\n\tiamCreatePermission (payload:$payload)\n\t{\n\t\tid\n\t\tname\n\t\tboundedContextId\n\t}\n}",
                        "variables": "{\n\t\"payload\":\n\t{\n\t\t\"id\": \"5b19d6ac-4081-573b-96b3-56964d5326a8\", \n\t\t\"name\": \"Licensed Steel Cheese\", \n\t\t\"boundedContextId\": \"5b19d6ac-4081-573b-96b3-56964d5326a8\"\n\t}\n}"
					}
				},
				"url": {
					"raw": "{{URL}}/graphql",
					"host": [
						"{{URL}}"
					],
					"path": [
						"graphql"
					]
				}
			},
			"response": []
        },
        {
			"name": "GraphQL - iamCreatePermissions",
			"request": {
				"method": "POST",
				"header": [],
				"body": {
					"mode": "graphql",
					"graphql": {
						"query": "mutation ($payload:[IamCreatePermissionInput]!)\n{\n\tiamCreatePermissions (payload:$payload)\n}",
						"variables": "{\n\t\"payload\":\n\t[\n\t\t{\n\t\t\t\"id\": \"ea8a08d2-ffdf-4ccf-94bc-ce347afc1a4f\", \n\t\t\t\"name\": \"Fantastic Soft Sausages\", \n\t\t\t\"boundedContextId\": \"75973434-4806-4f8a-9cba-40c78e005a55\"\n\t\t}, \n\t\t{\n\t\t\t\"id\": \"25e2167d-b2b1-4d52-b80d-6e5078b44e38\", \n\t\t\t\"name\": \"Incredible Plastic Salad\", \n\t\t\t\"boundedContextId\": \"f613be4c-84f2-492d-b8c4-9e065c2498f2\"\n\t\t}, \n\t\t{\n\t\t\t\"id\": \"a230969e-065f-48ca-8efa-abc91795a999\", \n\t\t\t\"name\": \"Small Cotton Chair\", \n\t\t\t\"boundedContextId\": \"545671ea-3d0f-435c-89b7-badf6aaae862\"\n\t\t}, \n\t\t{\n\t\t\t\"id\": \"d942b02b-e381-43fa-a263-fadd2e442c3b\", \n\t\t\t\"name\": \"Sleek Metal Ball\", \n\t\t\t\"boundedContextId\": \"1169530f-29b5-40dd-aee6-635430520d7c\"\n\t\t}, \n\t\t{\n\t\t\t\"id\": \"d0f30fb1-22b3-4a63-bb73-9b5c58861c36\", \n\t\t\t\"name\": \"Incredible Granite Pizza\", \n\t\t\t\"boundedContextId\": \"0f8fe16a-296b-4506-8cee-314a53042625\"\n\t\t}, \n\t\t{\n\t\t\t\"id\": \"2dde7c23-6645-49a3-ac36-bbeec984eae3\", \n\t\t\t\"name\": \"Awesome Wooden Mouse\", \n\t\t\t\"boundedContextId\": \"beab4a20-0853-45d3-837d-07a0d5859a1f\"\n\t\t}, \n\t\t{\n\t\t\t\"id\": \"44c47441-eee7-4f3b-8265-c072a5b9b47a\", \n\t\t\t\"name\": \"Small Steel Pants\", \n\t\t\t\"boundedContextId\": \"ffd3d213-e3d4-404c-9288-d6dfd90d59f4\"\n\t\t}, \n\t\t{\n\t\t\t\"id\": \"ed78442b-7d06-475a-8811-b7624eb9c290\", \n\t\t\t\"name\": \"Sleek Fresh Hat\", \n\t\t\t\"boundedContextId\": \"1781dcaa-d6b2-4566-9722-95d2dc806d27\"\n\t\t}, \n\t\t{\n\t\t\t\"id\": \"712ee8b0-e2be-4359-b33e-5d8ccef4b629\", \n\t\t\t\"name\": \"Sleek Steel Ball\", \n\t\t\t\"boundedContextId\": \"fea3c82c-aabd-447a-a335-99c78e652e9d\"\n\t\t}, \n\t\t{\n\t\t\t\"id\": \"0d0b2df3-fb90-4bcb-a6a4-60ef0fed2cda\", \n\t\t\t\"name\": \"Sleek Frozen Towels\", \n\t\t\t\"boundedContextId\": \"cb070dcb-b771-40bb-ba67-688ac003abdb\"\n\t\t}\n\t]\n}"
					}
				},
				"url": {
					"raw": "{{URL}}/graphql",
					"host": [
						"{{URL}}"
					],
					"path": [
						"graphql"
					]
				}
			},
			"response": []
        },
        {
			"name": "GraphQL - iamPaginatePermissions",
			"request": {
				"method": "POST",
				"header": [
                ],
				"body": {
					"mode": "graphql",
					"graphql": {
						"query": "query ($query:QueryStatement $constraint:QueryStatement)\n{\n\tiamPaginatePermissions (query:$query constraint:$constraint)\n\t{\n\t\ttotal\n\t\tcount\n\t\trows\n\t}\n}",
						"variables": "{\n\t\"query\":\n\t{\n\t\t\"offset\": 0,\n\t\t\"limit\": 10\n\t}\n}"
					}
				},
				"url": {
					"raw": "{{URL}}/graphql",
					"host": [
						"{{URL}}"
					],
					"path": [
						"graphql"
					]
				}
			},
			"response": []
        },
        {
			"name": "GraphQL - iamGetPermissions",
			"request": {
				"method": "POST",
				"header": [
                ],
				"body": {
					"mode": "graphql",
					"graphql": {
						"query": "query ($query:QueryStatement)\n{\n\tiamGetPermissions (query: $query)\n\t{\n\t\tid\n\t\tname\n\t\tcreatedAt\n\t\tupdatedAt\n\t}\n}",
						"variables": "{\n\t\"query\":\n\t{\n\t\t\"where\":\n\t\t{ \n\t\t\t\"id\": \"5b19d6ac-4081-573b-96b3-56964d5326a8\"\n\t\t}\n\t}\n}"
					}
				},
				"url": {
					"raw": "{{URL}}/graphql",
					"host": [
						"{{URL}}"
					],
					"path": [
						"graphql"
					]
				}
			},
			"response": []
        },
        {
			"name": "GraphQL - iamFindPermission",
			"request": {
				"method": "POST",
				"header": [
                ],
				"body": {
					"mode": "graphql",
					"graphql": {
						"query": "query ($query:QueryStatement)\n{\n\tiamFindPermission (query: $query)\n\t{\n\t\tid\n\t\tname\n\t\tcreatedAt\n\t\tupdatedAt\n\t}\n}",
						"variables": "{\n\t\"query\":\n\t{\n\t\t\"where\":\n\t\t{\n\t\t\t\"id\": \"5b19d6ac-4081-573b-96b3-56964d5326a8\"\n\t\t}\n\t}\n}"
					}
				},
				"url": {
					"raw": "{{URL}}/graphql",
					"host": [
						"{{URL}}"
					],
					"path": [
						"graphql"
					]
				}
			},
			"response": []
        },
        {
			"name": "GraphQL - iamFindPermissionById",
			"request": {
				"method": "POST",
				"header": [
                ],
				"body": {
					"mode": "graphql",
					"graphql": {
						"query": "query ($id:ID)\n{\n\tiamFindPermissionById (id:$id)\n\t{\n\t\tid\n\t\tname\n\t\tcreatedAt\n\t\tupdatedAt\n\t}\n}",
						"variables": "{\n\t\"id\": \"5b19d6ac-4081-573b-96b3-56964d5326a8\"\n}"
					}
				},
				"url": {
					"raw": "{{URL}}/graphql",
					"host": [
						"{{URL}}"
					],
					"path": [
						"graphql"
					]
				}
			},
			"response": []
        },
        {
			"name": "GraphQL - iamUpdatePermission",
			"request": {
				"method": "POST",
				"header": [
                ],
				"body": {
					"mode": "graphql",
					"graphql": {
						"query": "mutation ($payload:IamUpdatePermissionInput!)\n{\n\tiamUpdatePermission (payload:$payload)\n\t{\n\t\tid\n\t\tname\n\t\tcreatedAt\n\t\tupdatedAt\n\t}\n}",
						"variables": "{\n\t\"payload\":\n\t{\n\t\t\"id\": \"5b19d6ac-4081-573b-96b3-56964d5326a8\", \n\t\t\"name\": \"Handcrafted Metal Pants\", \n\t\t\"boundedContextId\": \"5b19d6ac-4081-573b-96b3-56964d5326a8\", \n\t\t\"roleIds\": []\n\t}\n}"
					}
				},
				"url": {
					"raw": "{{URL}}/graphql",
					"host": [
						"{{URL}}"
					],
					"path": [
						"graphql"
					]
				}
			},
			"response": []
        },
        {
			"name": "GraphQL - iamDeletePermissionById",
			"request": {
				"method": "POST",
				"header": [
                ],
				"body": {
					"mode": "graphql",
					"graphql": {
						"query": "mutation ($id:ID!)\n{\n\tiamDeletePermissionById (id:$id)\n\t{\n\t\tid\n\t\tname\n\t\tcreatedAt\n\t\tupdatedAt\n\t}\n}",
						"variables": "{\n\t\"id\": \"5b19d6ac-4081-573b-96b3-56964d5326a8\"\n}"
					}
				},
				"url": {
					"raw": "{{URL}}/graphql",
					"host": [
						"{{URL}}"
					],
					"path": [
						"graphql"
					]
				}
			},
			"response": []
        },
        {
			"name": "GraphQL - iamDeletePermissions",
			"request": {
				"method": "POST",
				"header": [
                ],
				"body": {
					"mode": "graphql",
					"graphql": {
						"query": "mutation ($query:QueryStatement)\n{\n\tiamDeletePermissions (query: $query)\n\t{\n\t\tid\n\t\tname\n\t\tcreatedAt\n\t\tupdatedAt\n\t}\n}",
						"variables": "{\n\t\"query\":\n\t{\n\t\t\"where\":\n\t\t{\n\t\t\t\"id\":\n\t\t\t{\n\t\t\t\t\"[substring]\": \"\"\n\t\t\t}\n\t\t}\n\t}\n}"
					}
				},
				"url": {
					"raw": "{{URL}}/graphql",
					"host": [
						"{{URL}}"
					],
					"path": [
						"graphql"
					]
				}
			},
			"response": []
        },
        {
			"name": "REST - iam/permission/create",
			"request": {
				"method": "POST",
				"header": [
					{
						"key"   : "Content-Type",
						"name"  : "Content-Type",
						"type"  : "text",
						"value" : "application/json"
					}				],
				"body": {
					"mode"  : "raw",
					"raw"   : "{\n\t\"id\": \"5b19d6ac-4081-573b-96b3-56964d5326a8\", \n\t\"name\": \"Rustic Fresh Bacon\", \n\t\"boundedContextId\": \"5b19d6ac-4081-573b-96b3-56964d5326a8\", \n\t\"roleIds\": []\n}",
					"options": {
						"raw": {
							"language": "json"
						}
					}
				},
				"url": {
					"raw": "{{URL}}/iam/permission/create",
					"host": [
						"{{URL}}"
					],
					"path": [
						"iam",
						"permission",
                        "create"
					]
				}
			},
			"response": []
        },
        {
			"name": "REST - iam/permissions/create",
			"request": {
				"method": "POST",
				"header": [
					{
						"key"   : "Content-Type",
						"name"  : "Content-Type",
						"type"  : "text",
						"value" : "application/json"
					}				],
				"body": {
					"mode"  : "raw",
					"raw"   : "[\n\t{\n\t\t\"id\": \"8cc51775-17bf-4c2e-a5cc-4de52b5ddee1\", \n\t\t\"name\": \"Generic Plastic Chips\", \n\t\t\"boundedContextId\": \"799691be-9e8d-4acc-8937-66391f3feb7a\", \n\t\t\"roleIds\": []\n\t}, \n\t{\n\t\t\"id\": \"e955e501-46a8-4640-af53-036372ffedf3\", \n\t\t\"name\": \"Awesome Concrete Soap\", \n\t\t\"boundedContextId\": \"0a6261d1-c4a4-4bdc-852f-9655350523e7\", \n\t\t\"roleIds\": []\n\t}, \n\t{\n\t\t\"id\": \"1713808d-be28-4cd0-b24a-76a9e1738a58\", \n\t\t\"name\": \"Ergonomic Rubber Bacon\", \n\t\t\"boundedContextId\": \"74b89656-1e09-43c3-b013-fccb8ea1747f\", \n\t\t\"roleIds\": []\n\t}, \n\t{\n\t\t\"id\": \"fb1e542c-139f-4081-915e-95c5f925be9b\", \n\t\t\"name\": \"Small Steel Chips\", \n\t\t\"boundedContextId\": \"3a96f7c6-be7d-45a5-9e4d-9f4362c414f2\", \n\t\t\"roleIds\": []\n\t}, \n\t{\n\t\t\"id\": \"8b613564-e7ae-4a46-9ca0-2ebf864664f8\", \n\t\t\"name\": \"Handmade Fresh Table\", \n\t\t\"boundedContextId\": \"f42b8b8f-8769-4ad5-95a8-0128898c4075\", \n\t\t\"roleIds\": []\n\t}, \n\t{\n\t\t\"id\": \"74f02d8b-85b9-42ce-9fd1-6110dcd1e9bd\", \n\t\t\"name\": \"Handmade Wooden Car\", \n\t\t\"boundedContextId\": \"0f6719d3-0d9c-40ae-bfb9-6dac6ee99408\", \n\t\t\"roleIds\": []\n\t}, \n\t{\n\t\t\"id\": \"f4b0cb58-78ab-4134-86fd-50783e136041\", \n\t\t\"name\": \"Licensed Metal Fish\", \n\t\t\"boundedContextId\": \"eecfda3f-0399-4d31-abb5-d378b0e09540\", \n\t\t\"roleIds\": []\n\t}, \n\t{\n\t\t\"id\": \"e34e4d11-93b7-4d2c-93c1-5fe8430416ae\", \n\t\t\"name\": \"Fantastic Steel Tuna\", \n\t\t\"boundedContextId\": \"cef20130-8a3e-4cbe-8e8f-18462624fa92\", \n\t\t\"roleIds\": []\n\t}, \n\t{\n\t\t\"id\": \"c27541c4-7c6a-43eb-af06-7f9e4c29e39e\", \n\t\t\"name\": \"Fantastic Fresh Fish\", \n\t\t\"boundedContextId\": \"3d7ff7cf-b4f0-4182-b1ad-df087764ce8f\", \n\t\t\"roleIds\": []\n\t}, \n\t{\n\t\t\"id\": \"6992598d-4ac2-4c59-a20a-ea8caa563805\", \n\t\t\"name\": \"Intelligent Steel Keyboard\", \n\t\t\"boundedContextId\": \"45a67398-8c15-4b48-8db9-02d903f50d9d\", \n\t\t\"roleIds\": []\n\t}\n]",
					"options": {
						"raw": {
							"language": "json"
						}
					}
				},
				"url": {
					"raw": "{{URL}}/iam/permissions/create",
					"host": [
						"{{URL}}"
					],
					"path": [
						"iam",
						"permissions",
                        "create"
					]
				}
			},
			"response": []
        },
        {
			"name": "REST - iam/permissions/paginate",
			"protocolProfileBehavior": {
				"disableBodyPruning": true
			},
			"request": {
				"method": "POST",
				"header": [
					{
						"key": "Content-Type",
						"name": "Content-Type",
						"type": "text",
						"value": "application/json"
					}				],
				"body": {
					"mode": "raw",
					"raw": "{\n\t\"query\":\n\t{\n\t\t\"offset\": 0,\n\t\t\"limit\": 10\n\t}\n}",
					"options": {
						"raw": {
							"language": "json"
						}
					}
				},
				"url": {
					"raw": "{{URL}}/iam/permissions/paginate",
					"host": [
						"{{URL}}"
					],
					"path": [
						"iam",
                        "permissions",
                        "paginate"
					]
				}
			},
			"response": []
        },
        {
			"name": "REST - iam/permissions/get",
			"protocolProfileBehavior": {
				"disableBodyPruning": true
			},
			"request": {
				"method": "POST",
				"header": [
					{
						"key": "Content-Type",
						"name": "Content-Type",
						"type": "text",
						"value": "application/json"
					}				],
				"body": {
					"mode": "raw",
					"raw": "{\n\t\"query\":\n\t{\n\t\t\"where\":\n\t\t{ \n\t\t\t\"id\": \"5b19d6ac-4081-573b-96b3-56964d5326a8\"\n\t\t}\n\t}\n}",
					"options": {
						"raw": {
							"language": "json"
						}
					}
				},
				"url": {
					"raw": "{{URL}}/iam/permissions/get",
					"host": [
						"{{URL}}"
					],
					"path": [
						"iam",
						"permissions",
                        "get"
					]
				}
			},
			"response": []
        },
        {
			"name": "REST - iam/permission/find",
			"protocolProfileBehavior": {
				"disableBodyPruning": true
			},
			"request": {
				"method": "POST",
				"header": [
					{
						"key": "Content-Type",
						"name": "Content-Type",
						"type": "text",
						"value": "application/json"
					}				],
				"body": {
					"mode": "raw",
					"raw": "{\n\t\"query\":\n\t{\n\t\t\"where\":\n\t\t{\n\t\t\t\"id\": \"5b19d6ac-4081-573b-96b3-56964d5326a8\"\n\t\t}\n\t}\n}",
					"options": {
						"raw": {
							"language": "json"
						}
					}
				},
				"url": {
					"raw": "{{URL}}/iam/permission/find",
					"host": [
						"{{URL}}"
					],
					"path": [
						"iam",
						"permission",
                        "find"
					]
				}
			},
			"response": []
        },
        {
			"name": "REST - iam/permission/find/{id}",
			"protocolProfileBehavior": {
				"disableBodyPruning": true
			},
			"request": {
				"method": "POST",
				"header": [
					{
						"key": "Content-Type",
						"name": "Content-Type",
						"type": "text",
						"value": "application/json"
					}				],
				"body": {
					"mode": "raw",
					"raw": "",
					"options": {
						"raw": {
							"language": "json"
						}
					}
				},
				"url": {
					"raw": "{{URL}}/iam/permission/find/5b19d6ac-4081-573b-96b3-56964d5326a8",
					"host": [
						"{{URL}}"
					],
					"path": [
						"iam",
						"permission",
                        "find",
						"5b19d6ac-4081-573b-96b3-56964d5326a8"
					]
				}
			},
			"response": []
        },
        {
			"name": "REST - iam/permission/update",
			"request": {
				"method": "PUT",
				"header": [
					{
						"key": "Content-Type",
						"name": "Content-Type",
						"type": "text",
						"value": "application/json"
					}				],
				"body": {
					"mode": "raw",
					"raw"   : "{\n\t\"id\": \"5b19d6ac-4081-573b-96b3-56964d5326a8\", \n\t\"name\": \"Fantastic Metal Bike\", \n\t\"boundedContextId\": \"5b19d6ac-4081-573b-96b3-56964d5326a8\", \n\t\"roleIds\": []\n}",
					"options": {
						"raw": {
							"language": "json"
						}
					}
				},
				"url": {
					"raw": "{{URL}}/iam/permission/update",
					"host": [
						"{{URL}}"
					],
					"path": [
						"iam",
						"permission",
                        "update"
					]
				}
			},
			"response": []
        },
        {
			"name": "REST - iam/permission/delete/{id}",
			"request": {
				"method": "DELETE",
				"header": [
					{
						"key": "Content-Type",
						"name": "Content-Type",
						"type": "text",
						"value": "application/json"
					}				],
				"body": {
					"mode": "raw",
					"raw": "",
					"options": {
						"raw": {
							"language": "json"
						}
					}
				},
				"url": {
					"raw": "{{URL}}/iam/permission/delete/5b19d6ac-4081-573b-96b3-56964d5326a8",
					"host": [
						"{{URL}}"
					],
					"path": [
						"iam",
						"permission",
                        "delete",
						"5b19d6ac-4081-573b-96b3-56964d5326a8"
					]
				}
			},
			"response": []
		},
        {
			"name": "REST - iam/permissions/delete",
			"request": {
				"method": "DELETE",
				"header": [
					{
						"key": "Content-Type",
						"name": "Content-Type",
						"type": "text",
						"value": "application/json"
					}				],
				"body": {
					"mode": "raw",
					"raw": "{\n\t\"query\":\n\t{\n\t\t\"where\":\n\t\t{\n\t\t\t\"id\":\n\t\t\t{\n\t\t\t\t\"[substring]\": \"\"\n\t\t\t}\n\t\t}\n\t}\n}",
					"options": {
						"raw": {
							"language": "json"
						}
					}
				},
				"url": {
					"raw": "{{URL}}/iam/permissions/delete",
					"host": [
						"{{URL}}"
					],
					"path": [
						"iam",
						"permissions",
                        "delete"
					]
				}
			},
			"response": []
		}
    ],
    "variable": [
		{
			"id": "d9bc3afc-fd40-5505-b57f-8f5d5118e01b",
			"key": "URL",
			"value": "http://localhost:8080",
			"type": "string"
		}
	]
}