{
    "info": {
		"_postman_id"   : "d9bc3afc-fd40-5505-b57f-8f5d5118e01b",
		"name"          : "@app - iam/tag",
		"schema"        : "https://schema.getpostman.com/json/collection/v2.1.0/collection.json"
    },
    "item": [
        {
			"name": "GraphQL - iamCreateTag",
			"request": {
				"method": "POST",
				"header": [
                ],
				"body": {
					"mode": "graphql",
					"graphql": {
						"query": "mutation ($payload:IamCreateTagInput!)\n{\n\tiamCreateTag (payload:$payload)\n\t{\n\t\tid\n\t\tname\n\t}\n}",
                        "variables": "{\n\t\"payload\":\n\t{\n\t\t\"id\": \"5b19d6ac-4081-573b-96b3-56964d5326a8\", \n\t\t\"name\": \"Refined Soft Shirt\"\n\t}\n}"
					}
				},
				"url": {
					"raw": "{{URL}}/graphql",
					"host": [
						"{{URL}}"
					],
					"path": [
						"graphql"
					]
				}
			},
			"response": []
        },
        {
			"name": "GraphQL - iamCreateTags",
			"request": {
				"method": "POST",
				"header": [],
				"body": {
					"mode": "graphql",
					"graphql": {
						"query": "mutation ($payload:[IamCreateTagInput]!)\n{\n\tiamCreateTags (payload:$payload)\n}",
						"variables": "{\n\t\"payload\":\n\t[\n\t\t{\n\t\t\t\"id\": \"2391d905-3be2-4d94-8f8f-f7c37d558b32\", \n\t\t\t\"name\": \"Gorgeous Soft Mouse\"\n\t\t}, \n\t\t{\n\t\t\t\"id\": \"35f94d35-228d-4b40-b1c9-7171f8370b09\", \n\t\t\t\"name\": \"Awesome Frozen Shirt\"\n\t\t}, \n\t\t{\n\t\t\t\"id\": \"8c7bb057-381a-4a89-b41a-55fa2c434f70\", \n\t\t\t\"name\": \"Practical Wooden Chips\"\n\t\t}, \n\t\t{\n\t\t\t\"id\": \"4dbca2d2-d344-4f2e-ae64-6d0edb217f9f\", \n\t\t\t\"name\": \"Unbranded Metal Hat\"\n\t\t}, \n\t\t{\n\t\t\t\"id\": \"780e4728-b719-4ede-a125-c82c6df17a8c\", \n\t\t\t\"name\": \"Refined Rubber Mouse\"\n\t\t}, \n\t\t{\n\t\t\t\"id\": \"9f9a8dbf-d55b-4dde-82f0-44720b931854\", \n\t\t\t\"name\": \"Tasty Soft Soap\"\n\t\t}, \n\t\t{\n\t\t\t\"id\": \"5e9c5136-e251-492c-b8a5-c56f2c75decc\", \n\t\t\t\"name\": \"Awesome Steel Bacon\"\n\t\t}, \n\t\t{\n\t\t\t\"id\": \"b816311e-f659-42a7-a452-acb6df796660\", \n\t\t\t\"name\": \"Fantastic Frozen Towels\"\n\t\t}, \n\t\t{\n\t\t\t\"id\": \"f22ff61d-7a99-4707-aaa4-6a29b1037698\", \n\t\t\t\"name\": \"Gorgeous Steel Chair\"\n\t\t}, \n\t\t{\n\t\t\t\"id\": \"e6eaaa1e-deab-4d2e-b532-48a55931b3de\", \n\t\t\t\"name\": \"Gorgeous Frozen Table\"\n\t\t}\n\t]\n}"
					}
				},
				"url": {
					"raw": "{{URL}}/graphql",
					"host": [
						"{{URL}}"
					],
					"path": [
						"graphql"
					]
				}
			},
			"response": []
        },
        {
			"name": "GraphQL - iamPaginateTags",
			"request": {
				"method": "POST",
				"header": [
                ],
				"body": {
					"mode": "graphql",
					"graphql": {
						"query": "query ($query:QueryStatement $constraint:QueryStatement)\n{\n\tiamPaginateTags (query:$query constraint:$constraint)\n\t{\n\t\ttotal\n\t\tcount\n\t\trows\n\t}\n}",
						"variables": "{\n\t\"query\":\n\t{\n\t\t\"offset\": 0,\n\t\t\"limit\": 10\n\t}\n}"
					}
				},
				"url": {
					"raw": "{{URL}}/graphql",
					"host": [
						"{{URL}}"
					],
					"path": [
						"graphql"
					]
				}
			},
			"response": []
        },
        {
			"name": "GraphQL - iamGetTags",
			"request": {
				"method": "POST",
				"header": [
                ],
				"body": {
					"mode": "graphql",
					"graphql": {
						"query": "query ($query:QueryStatement)\n{\n\tiamGetTags (query: $query)\n\t{\n\t\tid\n\t\tname\n\t\tcreatedAt\n\t\tupdatedAt\n\t}\n}",
						"variables": "{\n\t\"query\":\n\t{\n\t\t\"where\":\n\t\t{ \n\t\t\t\"id\": \"5b19d6ac-4081-573b-96b3-56964d5326a8\"\n\t\t}\n\t}\n}"
					}
				},
				"url": {
					"raw": "{{URL}}/graphql",
					"host": [
						"{{URL}}"
					],
					"path": [
						"graphql"
					]
				}
			},
			"response": []
        },
        {
			"name": "GraphQL - iamFindTag",
			"request": {
				"method": "POST",
				"header": [
                ],
				"body": {
					"mode": "graphql",
					"graphql": {
						"query": "query ($query:QueryStatement)\n{\n\tiamFindTag (query: $query)\n\t{\n\t\tid\n\t\tname\n\t\tcreatedAt\n\t\tupdatedAt\n\t}\n}",
						"variables": "{\n\t\"query\":\n\t{\n\t\t\"where\":\n\t\t{\n\t\t\t\"id\": \"5b19d6ac-4081-573b-96b3-56964d5326a8\"\n\t\t}\n\t}\n}"
					}
				},
				"url": {
					"raw": "{{URL}}/graphql",
					"host": [
						"{{URL}}"
					],
					"path": [
						"graphql"
					]
				}
			},
			"response": []
        },
        {
			"name": "GraphQL - iamFindTagById",
			"request": {
				"method": "POST",
				"header": [
                ],
				"body": {
					"mode": "graphql",
					"graphql": {
						"query": "query ($id:ID)\n{\n\tiamFindTagById (id:$id)\n\t{\n\t\tid\n\t\tname\n\t\tcreatedAt\n\t\tupdatedAt\n\t}\n}",
						"variables": "{\n\t\"id\": \"5b19d6ac-4081-573b-96b3-56964d5326a8\"\n}"
					}
				},
				"url": {
					"raw": "{{URL}}/graphql",
					"host": [
						"{{URL}}"
					],
					"path": [
						"graphql"
					]
				}
			},
			"response": []
        },
        {
			"name": "GraphQL - iamUpdateTag",
			"request": {
				"method": "POST",
				"header": [
                ],
				"body": {
					"mode": "graphql",
					"graphql": {
						"query": "mutation ($payload:IamUpdateTagInput!)\n{\n\tiamUpdateTag (payload:$payload)\n\t{\n\t\tid\n\t\tname\n\t\tcreatedAt\n\t\tupdatedAt\n\t}\n}",
						"variables": "{\n\t\"payload\":\n\t{\n\t\t\"id\": \"5b19d6ac-4081-573b-96b3-56964d5326a8\", \n\t\t\"name\": \"Unbranded Rubber Pizza\"\n\t}\n}"
					}
				},
				"url": {
					"raw": "{{URL}}/graphql",
					"host": [
						"{{URL}}"
					],
					"path": [
						"graphql"
					]
				}
			},
			"response": []
        },
        {
			"name": "GraphQL - iamDeleteTagById",
			"request": {
				"method": "POST",
				"header": [
                ],
				"body": {
					"mode": "graphql",
					"graphql": {
						"query": "mutation ($id:ID!)\n{\n\tiamDeleteTagById (id:$id)\n\t{\n\t\tid\n\t\tname\n\t\tcreatedAt\n\t\tupdatedAt\n\t}\n}",
						"variables": "{\n\t\"id\": \"5b19d6ac-4081-573b-96b3-56964d5326a8\"\n}"
					}
				},
				"url": {
					"raw": "{{URL}}/graphql",
					"host": [
						"{{URL}}"
					],
					"path": [
						"graphql"
					]
				}
			},
			"response": []
        },
        {
			"name": "GraphQL - iamDeleteTags",
			"request": {
				"method": "POST",
				"header": [
                ],
				"body": {
					"mode": "graphql",
					"graphql": {
						"query": "mutation ($query:QueryStatement)\n{\n\tiamDeleteTags (query: $query)\n\t{\n\t\tid\n\t\tname\n\t\tcreatedAt\n\t\tupdatedAt\n\t}\n}",
						"variables": "{\n\t\"query\":\n\t{\n\t\t\"where\":\n\t\t{\n\t\t\t\"id\":\n\t\t\t{\n\t\t\t\t\"[substring]\": \"\"\n\t\t\t}\n\t\t}\n\t}\n}"
					}
				},
				"url": {
					"raw": "{{URL}}/graphql",
					"host": [
						"{{URL}}"
					],
					"path": [
						"graphql"
					]
				}
			},
			"response": []
        },
        {
			"name": "REST - iam/tag/create",
			"request": {
				"method": "POST",
				"header": [
					{
						"key"   : "Content-Type",
						"name"  : "Content-Type",
						"type"  : "text",
						"value" : "application/json"
					}				],
				"body": {
					"mode"  : "raw",
					"raw"   : "{\n\t\"id\": \"5b19d6ac-4081-573b-96b3-56964d5326a8\", \n\t\"name\": \"Licensed Rubber Ball\"\n}",
					"options": {
						"raw": {
							"language": "json"
						}
					}
				},
				"url": {
					"raw": "{{URL}}/iam/tag/create",
					"host": [
						"{{URL}}"
					],
					"path": [
						"iam",
						"tag",
                        "create"
					]
				}
			},
			"response": []
        },
        {
			"name": "REST - iam/tags/create",
			"request": {
				"method": "POST",
				"header": [
					{
						"key"   : "Content-Type",
						"name"  : "Content-Type",
						"type"  : "text",
						"value" : "application/json"
					}				],
				"body": {
					"mode"  : "raw",
					"raw"   : "[\n\t{\n\t\t\"id\": \"51f5c2d9-7559-4586-a9ca-8df9e7ce0d37\", \n\t\t\"name\": \"Awesome Rubber Towels\"\n\t}, \n\t{\n\t\t\"id\": \"7e080e89-f62b-4801-8d04-ed967244beac\", \n\t\t\"name\": \"Small Wooden Shoes\"\n\t}, \n\t{\n\t\t\"id\": \"51473699-14a9-49d4-a4ca-3b4110f9fd3c\", \n\t\t\"name\": \"Fantastic Wooden Chair\"\n\t}, \n\t{\n\t\t\"id\": \"5f3f922f-6045-4a16-a58f-fc586bf7422a\", \n\t\t\"name\": \"Unbranded Steel Shoes\"\n\t}, \n\t{\n\t\t\"id\": \"1dadfefb-9e48-40f3-88ed-ad9fe7e0b2ed\", \n\t\t\"name\": \"Rustic Rubber Pants\"\n\t}, \n\t{\n\t\t\"id\": \"eef4d9e6-6e00-429c-bb38-ba0f81967129\", \n\t\t\"name\": \"Tasty Granite Car\"\n\t}, \n\t{\n\t\t\"id\": \"2dc28b8a-881a-449c-9b95-6f9bd868a7ea\", \n\t\t\"name\": \"Practical Metal Ball\"\n\t}, \n\t{\n\t\t\"id\": \"9e56f508-acd1-439a-80f5-d7ba3d2b69ef\", \n\t\t\"name\": \"Intelligent Granite Table\"\n\t}, \n\t{\n\t\t\"id\": \"adad6bf5-b88a-44dd-97b5-5743db98b50b\", \n\t\t\"name\": \"Intelligent Metal Keyboard\"\n\t}, \n\t{\n\t\t\"id\": \"4441c002-6a58-4828-b7d7-2699cb00ab8a\", \n\t\t\"name\": \"Generic Cotton Fish\"\n\t}\n]",
					"options": {
						"raw": {
							"language": "json"
						}
					}
				},
				"url": {
					"raw": "{{URL}}/iam/tags/create",
					"host": [
						"{{URL}}"
					],
					"path": [
						"iam",
						"tags",
                        "create"
					]
				}
			},
			"response": []
        },
        {
			"name": "REST - iam/tags/paginate",
			"protocolProfileBehavior": {
				"disableBodyPruning": true
			},
			"request": {
				"method": "POST",
				"header": [
					{
						"key": "Content-Type",
						"name": "Content-Type",
						"type": "text",
						"value": "application/json"
					}				],
				"body": {
					"mode": "raw",
					"raw": "{\n\t\"query\":\n\t{\n\t\t\"offset\": 0,\n\t\t\"limit\": 10\n\t}\n}",
					"options": {
						"raw": {
							"language": "json"
						}
					}
				},
				"url": {
					"raw": "{{URL}}/iam/tags/paginate",
					"host": [
						"{{URL}}"
					],
					"path": [
						"iam",
                        "tags",
                        "paginate"
					]
				}
			},
			"response": []
        },
        {
			"name": "REST - iam/tags/get",
			"protocolProfileBehavior": {
				"disableBodyPruning": true
			},
			"request": {
				"method": "POST",
				"header": [
					{
						"key": "Content-Type",
						"name": "Content-Type",
						"type": "text",
						"value": "application/json"
					}				],
				"body": {
					"mode": "raw",
					"raw": "{\n\t\"query\":\n\t{\n\t\t\"where\":\n\t\t{ \n\t\t\t\"id\": \"5b19d6ac-4081-573b-96b3-56964d5326a8\"\n\t\t}\n\t}\n}",
					"options": {
						"raw": {
							"language": "json"
						}
					}
				},
				"url": {
					"raw": "{{URL}}/iam/tags/get",
					"host": [
						"{{URL}}"
					],
					"path": [
						"iam",
						"tags",
                        "get"
					]
				}
			},
			"response": []
        },
        {
			"name": "REST - iam/tag/find",
			"protocolProfileBehavior": {
				"disableBodyPruning": true
			},
			"request": {
				"method": "POST",
				"header": [
					{
						"key": "Content-Type",
						"name": "Content-Type",
						"type": "text",
						"value": "application/json"
					}				],
				"body": {
					"mode": "raw",
					"raw": "{\n\t\"query\":\n\t{\n\t\t\"where\":\n\t\t{\n\t\t\t\"id\": \"5b19d6ac-4081-573b-96b3-56964d5326a8\"\n\t\t}\n\t}\n}",
					"options": {
						"raw": {
							"language": "json"
						}
					}
				},
				"url": {
					"raw": "{{URL}}/iam/tag/find",
					"host": [
						"{{URL}}"
					],
					"path": [
						"iam",
						"tag",
                        "find"
					]
				}
			},
			"response": []
        },
        {
			"name": "REST - iam/tag/find/{id}",
			"protocolProfileBehavior": {
				"disableBodyPruning": true
			},
			"request": {
				"method": "POST",
				"header": [
					{
						"key": "Content-Type",
						"name": "Content-Type",
						"type": "text",
						"value": "application/json"
					}				],
				"body": {
					"mode": "raw",
					"raw": "",
					"options": {
						"raw": {
							"language": "json"
						}
					}
				},
				"url": {
					"raw": "{{URL}}/iam/tag/find/5b19d6ac-4081-573b-96b3-56964d5326a8",
					"host": [
						"{{URL}}"
					],
					"path": [
						"iam",
						"tag",
                        "find",
						"5b19d6ac-4081-573b-96b3-56964d5326a8"
					]
				}
			},
			"response": []
        },
        {
			"name": "REST - iam/tag/update",
			"request": {
				"method": "PUT",
				"header": [
					{
						"key": "Content-Type",
						"name": "Content-Type",
						"type": "text",
						"value": "application/json"
					}				],
				"body": {
					"mode": "raw",
					"raw"   : "{\n\t\"id\": \"5b19d6ac-4081-573b-96b3-56964d5326a8\", \n\t\"name\": \"Rustic Frozen Car\"\n}",
					"options": {
						"raw": {
							"language": "json"
						}
					}
				},
				"url": {
					"raw": "{{URL}}/iam/tag/update",
					"host": [
						"{{URL}}"
					],
					"path": [
						"iam",
						"tag",
                        "update"
					]
				}
			},
			"response": []
        },
        {
			"name": "REST - iam/tag/delete/{id}",
			"request": {
				"method": "DELETE",
				"header": [
					{
						"key": "Content-Type",
						"name": "Content-Type",
						"type": "text",
						"value": "application/json"
					}				],
				"body": {
					"mode": "raw",
					"raw": "",
					"options": {
						"raw": {
							"language": "json"
						}
					}
				},
				"url": {
					"raw": "{{URL}}/iam/tag/delete/5b19d6ac-4081-573b-96b3-56964d5326a8",
					"host": [
						"{{URL}}"
					],
					"path": [
						"iam",
						"tag",
                        "delete",
						"5b19d6ac-4081-573b-96b3-56964d5326a8"
					]
				}
			},
			"response": []
		},
        {
			"name": "REST - iam/tags/delete",
			"request": {
				"method": "DELETE",
				"header": [
					{
						"key": "Content-Type",
						"name": "Content-Type",
						"type": "text",
						"value": "application/json"
					}				],
				"body": {
					"mode": "raw",
					"raw": "{\n\t\"query\":\n\t{\n\t\t\"where\":\n\t\t{\n\t\t\t\"id\":\n\t\t\t{\n\t\t\t\t\"[substring]\": \"\"\n\t\t\t}\n\t\t}\n\t}\n}",
					"options": {
						"raw": {
							"language": "json"
						}
					}
				},
				"url": {
					"raw": "{{URL}}/iam/tags/delete",
					"host": [
						"{{URL}}"
					],
					"path": [
						"iam",
						"tags",
                        "delete"
					]
				}
			},
			"response": []
		}
    ],
    "variable": [
		{
			"id": "d9bc3afc-fd40-5505-b57f-8f5d5118e01b",
			"key": "URL",
			"value": "http://localhost:8080",
			"type": "string"
		}
	]
}