{
    "info": {
		"_postman_id"   : "d9bc3afc-fd40-5505-b57f-8f5d5118e01b",
		"name"          : "@app - iam/permission",
		"schema"        : "https://schema.getpostman.com/json/collection/v2.1.0/collection.json"
    },
    "item": [
        {
			"name": "GraphQL - iamCreatePermission",
			"request": {
				"method": "POST",
				"header": [
                ],
				"body": {
					"mode": "graphql",
					"graphql": {
						"query": "mutation ($payload:IamCreatePermissionInput!)\n{\n\tiamCreatePermission (payload:$payload)\n\t{\n\t\tid\n\t\tname\n\t\tboundedContextId\n\t}\n}",
                        "variables": "{\n\t\"payload\":\n\t{\n\t\t\"id\": \"5b19d6ac-4081-573b-96b3-56964d5326a8\", \n\t\t\"name\": \"Gorgeous Wooden Pizza\", \n\t\t\"boundedContextId\": \"5b19d6ac-4081-573b-96b3-56964d5326a8\"\n\t}\n}"
					}
				},
				"url": {
					"raw": "{{URL}}/graphql",
					"host": [
						"{{URL}}"
					],
					"path": [
						"graphql"
					]
				}
			},
			"response": []
        },
        {
			"name": "GraphQL - iamCreatePermissions",
			"request": {
				"method": "POST",
				"header": [],
				"body": {
					"mode": "graphql",
					"graphql": {
						"query": "mutation ($payload:[IamCreatePermissionInput]!)\n{\n\tiamCreatePermissions (payload:$payload)\n}",
						"variables": "{\n\t\"payload\":\n\t[\n\t\t{\n\t\t\t\"id\": \"740a5b33-f122-47d9-bef8-fe222b347d57\", \n\t\t\t\"name\": \"Tasty Concrete Cheese\", \n\t\t\t\"boundedContextId\": \"b7ee86e5-2dc2-40e1-be07-c357843bc18a\"\n\t\t}, \n\t\t{\n\t\t\t\"id\": \"1edbda64-1470-4b34-89cf-409360c103a2\", \n\t\t\t\"name\": \"Fantastic Frozen Chair\", \n\t\t\t\"boundedContextId\": \"103d0430-55ed-4256-ac8e-5253ddb09381\"\n\t\t}, \n\t\t{\n\t\t\t\"id\": \"95a5d78f-393d-4640-bddd-7e5cbdd2118d\", \n\t\t\t\"name\": \"Refined Concrete Car\", \n\t\t\t\"boundedContextId\": \"e7ba6a2a-a9c4-4092-8e83-871abf86d764\"\n\t\t}, \n\t\t{\n\t\t\t\"id\": \"db17ec9e-95f9-460d-9ef6-7fd780385d6b\", \n\t\t\t\"name\": \"Handcrafted Plastic Chips\", \n\t\t\t\"boundedContextId\": \"615536d3-166d-43f5-b268-7e6ffa207245\"\n\t\t}, \n\t\t{\n\t\t\t\"id\": \"30aadbb9-1fa5-4ab7-8e17-e33eecf9095f\", \n\t\t\t\"name\": \"Unbranded Rubber Chair\", \n\t\t\t\"boundedContextId\": \"13057fb4-8d92-4786-88b5-0a6ae3fcfd30\"\n\t\t}, \n\t\t{\n\t\t\t\"id\": \"752bf49d-3d74-4baa-8d25-d15ec30e830e\", \n\t\t\t\"name\": \"Unbranded Rubber Keyboard\", \n\t\t\t\"boundedContextId\": \"36aa33f3-064c-4de6-8a53-1fa7aa9f715c\"\n\t\t}, \n\t\t{\n\t\t\t\"id\": \"d0223543-d63a-4226-ad69-c771b088a3f3\", \n\t\t\t\"name\": \"Practical Soft Car\", \n\t\t\t\"boundedContextId\": \"03882edc-1938-40fc-9b83-5b3324edbb6a\"\n\t\t}, \n\t\t{\n\t\t\t\"id\": \"29df2121-4f28-4d57-97c0-104d871b444e\", \n\t\t\t\"name\": \"Sleek Frozen Soap\", \n\t\t\t\"boundedContextId\": \"e52910b5-e7cf-4efa-aa82-ec275d3c6df8\"\n\t\t}, \n\t\t{\n\t\t\t\"id\": \"91d270f9-b097-4632-8cae-7dd9944bac9b\", \n\t\t\t\"name\": \"Rustic Concrete Ball\", \n\t\t\t\"boundedContextId\": \"c8ec56d1-33fa-4816-81d6-871ea9fdfc17\"\n\t\t}, \n\t\t{\n\t\t\t\"id\": \"ed2c7cef-2fc9-4128-916e-0af612025a03\", \n\t\t\t\"name\": \"Unbranded Fresh Fish\", \n\t\t\t\"boundedContextId\": \"0132050d-1b72-4cb6-ba45-3f61671b2c1e\"\n\t\t}\n\t]\n}"
					}
				},
				"url": {
					"raw": "{{URL}}/graphql",
					"host": [
						"{{URL}}"
					],
					"path": [
						"graphql"
					]
				}
			},
			"response": []
        },
        {
			"name": "GraphQL - iamPaginatePermissions",
			"request": {
				"method": "POST",
				"header": [
                ],
				"body": {
					"mode": "graphql",
					"graphql": {
						"query": "query ($query:QueryStatement $constraint:QueryStatement)\n{\n\tiamPaginatePermissions (query:$query constraint:$constraint)\n\t{\n\t\ttotal\n\t\tcount\n\t\trows\n\t}\n}",
						"variables": "{\n\t\"query\":\n\t{\n\t\t\"offset\": 0,\n\t\t\"limit\": 10\n\t}\n}"
					}
				},
				"url": {
					"raw": "{{URL}}/graphql",
					"host": [
						"{{URL}}"
					],
					"path": [
						"graphql"
					]
				}
			},
			"response": []
        },
        {
			"name": "GraphQL - iamGetPermissions",
			"request": {
				"method": "POST",
				"header": [
                ],
				"body": {
					"mode": "graphql",
					"graphql": {
						"query": "query ($query:QueryStatement)\n{\n\tiamGetPermissions (query: $query)\n\t{\n\t\tid\n\t\tname\n\t\tcreatedAt\n\t\tupdatedAt\n\t}\n}",
						"variables": "{\n\t\"query\":\n\t{\n\t\t\"where\":\n\t\t{ \n\t\t\t\"id\": \"5b19d6ac-4081-573b-96b3-56964d5326a8\"\n\t\t}\n\t}\n}"
					}
				},
				"url": {
					"raw": "{{URL}}/graphql",
					"host": [
						"{{URL}}"
					],
					"path": [
						"graphql"
					]
				}
			},
			"response": []
        },
        {
			"name": "GraphQL - iamFindPermission",
			"request": {
				"method": "POST",
				"header": [
                ],
				"body": {
					"mode": "graphql",
					"graphql": {
						"query": "query ($query:QueryStatement)\n{\n\tiamFindPermission (query: $query)\n\t{\n\t\tid\n\t\tname\n\t\tcreatedAt\n\t\tupdatedAt\n\t}\n}",
						"variables": "{\n\t\"query\":\n\t{\n\t\t\"where\":\n\t\t{\n\t\t\t\"id\": \"5b19d6ac-4081-573b-96b3-56964d5326a8\"\n\t\t}\n\t}\n}"
					}
				},
				"url": {
					"raw": "{{URL}}/graphql",
					"host": [
						"{{URL}}"
					],
					"path": [
						"graphql"
					]
				}
			},
			"response": []
        },
        {
			"name": "GraphQL - iamFindPermissionById",
			"request": {
				"method": "POST",
				"header": [
                ],
				"body": {
					"mode": "graphql",
					"graphql": {
						"query": "query ($id:ID)\n{\n\tiamFindPermissionById (id:$id)\n\t{\n\t\tid\n\t\tname\n\t\tcreatedAt\n\t\tupdatedAt\n\t}\n}",
						"variables": "{\n\t\"id\": \"5b19d6ac-4081-573b-96b3-56964d5326a8\"\n}"
					}
				},
				"url": {
					"raw": "{{URL}}/graphql",
					"host": [
						"{{URL}}"
					],
					"path": [
						"graphql"
					]
				}
			},
			"response": []
        },
        {
			"name": "GraphQL - iamUpdatePermission",
			"request": {
				"method": "POST",
				"header": [
                ],
				"body": {
					"mode": "graphql",
					"graphql": {
						"query": "mutation ($payload:IamUpdatePermissionInput!)\n{\n\tiamUpdatePermission (payload:$payload)\n\t{\n\t\tid\n\t\tname\n\t\tcreatedAt\n\t\tupdatedAt\n\t}\n}",
						"variables": "{\n\t\"payload\":\n\t{\n\t\t\"id\": \"5b19d6ac-4081-573b-96b3-56964d5326a8\", \n\t\t\"name\": \"Rustic Fresh Mouse\", \n\t\t\"boundedContextId\": \"5b19d6ac-4081-573b-96b3-56964d5326a8\", \n\t\t\"roleIds\": []\n\t}\n}"
					}
				},
				"url": {
					"raw": "{{URL}}/graphql",
					"host": [
						"{{URL}}"
					],
					"path": [
						"graphql"
					]
				}
			},
			"response": []
        },
        {
			"name": "GraphQL - iamDeletePermissionById",
			"request": {
				"method": "POST",
				"header": [
                ],
				"body": {
					"mode": "graphql",
					"graphql": {
						"query": "mutation ($id:ID!)\n{\n\tiamDeletePermissionById (id:$id)\n\t{\n\t\tid\n\t\tname\n\t\tcreatedAt\n\t\tupdatedAt\n\t}\n}",
						"variables": "{\n\t\"id\": \"5b19d6ac-4081-573b-96b3-56964d5326a8\"\n}"
					}
				},
				"url": {
					"raw": "{{URL}}/graphql",
					"host": [
						"{{URL}}"
					],
					"path": [
						"graphql"
					]
				}
			},
			"response": []
        },
        {
			"name": "GraphQL - iamDeletePermissions",
			"request": {
				"method": "POST",
				"header": [
                ],
				"body": {
					"mode": "graphql",
					"graphql": {
						"query": "mutation ($query:QueryStatement)\n{\n\tiamDeletePermissions (query: $query)\n\t{\n\t\tid\n\t\tname\n\t\tcreatedAt\n\t\tupdatedAt\n\t}\n}",
						"variables": "{\n\t\"query\":\n\t{\n\t\t\"where\":\n\t\t{\n\t\t\t\"id\":\n\t\t\t{\n\t\t\t\t\"[substring]\": \"\"\n\t\t\t}\n\t\t}\n\t}\n}"
					}
				},
				"url": {
					"raw": "{{URL}}/graphql",
					"host": [
						"{{URL}}"
					],
					"path": [
						"graphql"
					]
				}
			},
			"response": []
        },
        {
			"name": "REST - iam/permission/create",
			"request": {
				"method": "POST",
				"header": [
					{
						"key"   : "Content-Type",
						"name"  : "Content-Type",
						"type"  : "text",
						"value" : "application/json"
					}				],
				"body": {
					"mode"  : "raw",
					"raw"   : "{\n\t\"id\": \"5b19d6ac-4081-573b-96b3-56964d5326a8\", \n\t\"name\": \"Generic Metal Keyboard\", \n\t\"boundedContextId\": \"5b19d6ac-4081-573b-96b3-56964d5326a8\", \n\t\"roleIds\": []\n}",
					"options": {
						"raw": {
							"language": "json"
						}
					}
				},
				"url": {
					"raw": "{{URL}}/iam/permission/create",
					"host": [
						"{{URL}}"
					],
					"path": [
						"iam",
						"permission",
                        "create"
					]
				}
			},
			"response": []
        },
        {
			"name": "REST - iam/permissions/create",
			"request": {
				"method": "POST",
				"header": [
					{
						"key"   : "Content-Type",
						"name"  : "Content-Type",
						"type"  : "text",
						"value" : "application/json"
					}				],
				"body": {
					"mode"  : "raw",
					"raw"   : "[\n\t{\n\t\t\"id\": \"46d41bd4-142a-48c6-8cb3-7316cbb5c757\", \n\t\t\"name\": \"Fantastic Cotton Keyboard\", \n\t\t\"boundedContextId\": \"2eba1706-408a-4471-a55c-b03cbf6f76a2\", \n\t\t\"roleIds\": []\n\t}, \n\t{\n\t\t\"id\": \"8838e6cb-acec-4b7d-be8a-883d0a7c6cdb\", \n\t\t\"name\": \"Handmade Rubber Tuna\", \n\t\t\"boundedContextId\": \"bb9862ff-2681-459d-91f5-2b13939ab41e\", \n\t\t\"roleIds\": []\n\t}, \n\t{\n\t\t\"id\": \"d09e34d2-debf-4872-bf60-fbfac84ce9a1\", \n\t\t\"name\": \"Unbranded Granite Shirt\", \n\t\t\"boundedContextId\": \"b6096260-4045-424c-aad4-96901a7dbfb7\", \n\t\t\"roleIds\": []\n\t}, \n\t{\n\t\t\"id\": \"c4b4b02c-4ecd-4b81-9586-8996eae5039b\", \n\t\t\"name\": \"Tasty Soft Shoes\", \n\t\t\"boundedContextId\": \"078af57e-9adf-4696-a23f-126e207eed18\", \n\t\t\"roleIds\": []\n\t}, \n\t{\n\t\t\"id\": \"65dbf779-02a2-4c65-ba96-e3dcd48f21a0\", \n\t\t\"name\": \"Unbranded Metal Ball\", \n\t\t\"boundedContextId\": \"02316d4d-e6d0-49d8-8bfd-373162cf04c0\", \n\t\t\"roleIds\": []\n\t}, \n\t{\n\t\t\"id\": \"8dc5f8fc-c0a7-4c9d-8d5f-f63602f45bb3\", \n\t\t\"name\": \"Tasty Steel Car\", \n\t\t\"boundedContextId\": \"9c7f5af1-41d3-4d52-96e0-8f1f93937aff\", \n\t\t\"roleIds\": []\n\t}, \n\t{\n\t\t\"id\": \"bb431e7e-bc98-4b89-86a3-2d23f2d41445\", \n\t\t\"name\": \"Sleek Steel Towels\", \n\t\t\"boundedContextId\": \"185891e1-1013-4470-81da-181f8cf81ef4\", \n\t\t\"roleIds\": []\n\t}, \n\t{\n\t\t\"id\": \"9144cc67-3034-4c03-8600-057a5894496b\", \n\t\t\"name\": \"Incredible Granite Towels\", \n\t\t\"boundedContextId\": \"0750bb44-3608-465d-9a1f-2f42dbfbf69f\", \n\t\t\"roleIds\": []\n\t}, \n\t{\n\t\t\"id\": \"97f74191-fdcf-4d61-86a0-df0e830c587d\", \n\t\t\"name\": \"Handmade Steel Sausages\", \n\t\t\"boundedContextId\": \"5724d7ba-2109-43e5-990f-eb00d4a88d75\", \n\t\t\"roleIds\": []\n\t}, \n\t{\n\t\t\"id\": \"3b65fc4b-3365-41b7-b4df-bab628ecc963\", \n\t\t\"name\": \"Licensed Granite Car\", \n\t\t\"boundedContextId\": \"cce3d2f8-ded2-4468-b46e-ed4759e0a4f8\", \n\t\t\"roleIds\": []\n\t}\n]",
					"options": {
						"raw": {
							"language": "json"
						}
					}
				},
				"url": {
					"raw": "{{URL}}/iam/permissions/create",
					"host": [
						"{{URL}}"
					],
					"path": [
						"iam",
						"permissions",
                        "create"
					]
				}
			},
			"response": []
        },
        {
			"name": "REST - iam/permissions/paginate",
			"protocolProfileBehavior": {
				"disableBodyPruning": true
			},
			"request": {
				"method": "POST",
				"header": [
					{
						"key": "Content-Type",
						"name": "Content-Type",
						"type": "text",
						"value": "application/json"
					}				],
				"body": {
					"mode": "raw",
					"raw": "{\n\t\"query\":\n\t{\n\t\t\"offset\": 0,\n\t\t\"limit\": 10\n\t}\n}",
					"options": {
						"raw": {
							"language": "json"
						}
					}
				},
				"url": {
					"raw": "{{URL}}/iam/permissions/paginate",
					"host": [
						"{{URL}}"
					],
					"path": [
						"iam",
                        "permissions",
                        "paginate"
					]
				}
			},
			"response": []
        },
        {
			"name": "REST - iam/permissions/get",
			"protocolProfileBehavior": {
				"disableBodyPruning": true
			},
			"request": {
				"method": "POST",
				"header": [
					{
						"key": "Content-Type",
						"name": "Content-Type",
						"type": "text",
						"value": "application/json"
					}				],
				"body": {
					"mode": "raw",
					"raw": "{\n\t\"query\":\n\t{\n\t\t\"where\":\n\t\t{ \n\t\t\t\"id\": \"5b19d6ac-4081-573b-96b3-56964d5326a8\"\n\t\t}\n\t}\n}",
					"options": {
						"raw": {
							"language": "json"
						}
					}
				},
				"url": {
					"raw": "{{URL}}/iam/permissions/get",
					"host": [
						"{{URL}}"
					],
					"path": [
						"iam",
						"permissions",
                        "get"
					]
				}
			},
			"response": []
        },
        {
			"name": "REST - iam/permission/find",
			"protocolProfileBehavior": {
				"disableBodyPruning": true
			},
			"request": {
				"method": "POST",
				"header": [
					{
						"key": "Content-Type",
						"name": "Content-Type",
						"type": "text",
						"value": "application/json"
					}				],
				"body": {
					"mode": "raw",
					"raw": "{\n\t\"query\":\n\t{\n\t\t\"where\":\n\t\t{\n\t\t\t\"id\": \"5b19d6ac-4081-573b-96b3-56964d5326a8\"\n\t\t}\n\t}\n}",
					"options": {
						"raw": {
							"language": "json"
						}
					}
				},
				"url": {
					"raw": "{{URL}}/iam/permission/find",
					"host": [
						"{{URL}}"
					],
					"path": [
						"iam",
						"permission",
                        "find"
					]
				}
			},
			"response": []
        },
        {
			"name": "REST - iam/permission/find/{id}",
			"protocolProfileBehavior": {
				"disableBodyPruning": true
			},
			"request": {
				"method": "POST",
				"header": [
					{
						"key": "Content-Type",
						"name": "Content-Type",
						"type": "text",
						"value": "application/json"
					}				],
				"body": {
					"mode": "raw",
					"raw": "",
					"options": {
						"raw": {
							"language": "json"
						}
					}
				},
				"url": {
					"raw": "{{URL}}/iam/permission/find/5b19d6ac-4081-573b-96b3-56964d5326a8",
					"host": [
						"{{URL}}"
					],
					"path": [
						"iam",
						"permission",
                        "find",
						"5b19d6ac-4081-573b-96b3-56964d5326a8"
					]
				}
			},
			"response": []
        },
        {
			"name": "REST - iam/permission/update",
			"request": {
				"method": "PUT",
				"header": [
					{
						"key": "Content-Type",
						"name": "Content-Type",
						"type": "text",
						"value": "application/json"
					}				],
				"body": {
					"mode": "raw",
					"raw"   : "{\n\t\"id\": \"5b19d6ac-4081-573b-96b3-56964d5326a8\", \n\t\"name\": \"Incredible Frozen Chips\", \n\t\"boundedContextId\": \"5b19d6ac-4081-573b-96b3-56964d5326a8\", \n\t\"roleIds\": []\n}",
					"options": {
						"raw": {
							"language": "json"
						}
					}
				},
				"url": {
					"raw": "{{URL}}/iam/permission/update",
					"host": [
						"{{URL}}"
					],
					"path": [
						"iam",
						"permission",
                        "update"
					]
				}
			},
			"response": []
        },
        {
			"name": "REST - iam/permission/delete/{id}",
			"request": {
				"method": "DELETE",
				"header": [
					{
						"key": "Content-Type",
						"name": "Content-Type",
						"type": "text",
						"value": "application/json"
					}				],
				"body": {
					"mode": "raw",
					"raw": "",
					"options": {
						"raw": {
							"language": "json"
						}
					}
				},
				"url": {
					"raw": "{{URL}}/iam/permission/delete/5b19d6ac-4081-573b-96b3-56964d5326a8",
					"host": [
						"{{URL}}"
					],
					"path": [
						"iam",
						"permission",
                        "delete",
						"5b19d6ac-4081-573b-96b3-56964d5326a8"
					]
				}
			},
			"response": []
		},
        {
			"name": "REST - iam/permissions/delete",
			"request": {
				"method": "DELETE",
				"header": [
					{
						"key": "Content-Type",
						"name": "Content-Type",
						"type": "text",
						"value": "application/json"
					}				],
				"body": {
					"mode": "raw",
					"raw": "{\n\t\"query\":\n\t{\n\t\t\"where\":\n\t\t{\n\t\t\t\"id\":\n\t\t\t{\n\t\t\t\t\"[substring]\": \"\"\n\t\t\t}\n\t\t}\n\t}\n}",
					"options": {
						"raw": {
							"language": "json"
						}
					}
				},
				"url": {
					"raw": "{{URL}}/iam/permissions/delete",
					"host": [
						"{{URL}}"
					],
					"path": [
						"iam",
						"permissions",
                        "delete"
					]
				}
			},
			"response": []
		}
    ],
    "variable": [
		{
			"id": "d9bc3afc-fd40-5505-b57f-8f5d5118e01b",
			"key": "URL",
			"value": "http://localhost:8080",
			"type": "string"
		}
	]
}